rbxlx_export/__init__.py
rbxlx_export/extractor.py
rbxlx_export-1.0.0.dist-info/LICENSE
rbxlx_export-1.0.0.dist-info/METADATA
rbxlx_export-1.0.0.dist-info/WHEEL
rbxlx_export-1.0.0.dist-info/top_level.txt
rbxlx_export-1.0.0.dist-info/RECORD
