Metadata-Version: 2.1
Name: rbxlx-export
Version: 1.0.0
Summary: A tool to extract scripts from Roblox XML files.
Author: Your Name
Author-email: your.email@example.com
Classifier: Programming Language :: Python :: 3
License-File: LICENSE
Requires-Dist: xmltodict >=0.12.0
